setup.py
distributions_dataset/Binomialdistribution.py
distributions_dataset/Gaussiandistribution.py
distributions_dataset/Generaldistribution.py
distributions_dataset/__init__.py
distributions_dataset.egg-info/PKG-INFO
distributions_dataset.egg-info/SOURCES.txt
distributions_dataset.egg-info/dependency_links.txt
distributions_dataset.egg-info/not-zip-safe
distributions_dataset.egg-info/top_level.txt