Metadata-Version: 1.0
Name: distributions-dataset
Version: 1.1
Summary: Gaussian distributions
Home-page: UNKNOWN
Author: pratik_sheth
Author-email: psheth04@nyit.edu
License: UNKNOWN
Platform: UNKNOWN
